gelda/__init__.py
gelda/attribute_generation.py
gelda/vlm_evaluation.py
gelda-0.0.1.dist-info/LICENSE
gelda-0.0.1.dist-info/METADATA
gelda-0.0.1.dist-info/WHEEL
gelda-0.0.1.dist-info/top_level.txt
gelda-0.0.1.dist-info/RECORD
