Metadata-Version: 2.1
Name: gelda
Version: 0.0.1
Summary: GELDA: A generative language annotation framework to reveal visual biases in datasets
Author-email: Krish Kabra <kk80@rice.edu>, "Kathleen M. Lewis" <kmlewis@mit.edu>, Guha Balakrishnan <guha@rice.edu>
License: MIT License
Project-URL: Homepage, https://krishk97.github.io/publication/gelda
Project-URL: Repository, https://github.com/krishk97/gelda
Classifier: Development Status :: 3 - Alpha
Classifier: Intended Audience :: Science/Research
Classifier: Programming Language :: Python :: 3
Classifier: License :: OSI Approved :: BSD License
Classifier: Operating System :: OS Independent
Requires-Python: >=3.8
License-File: LICENSE
Requires-Dist: numpy >=1.24.3
Requires-Dist: torch >=2.0.1
Requires-Dist: torchvision >=0.15.2
Requires-Dist: transformers >=4.35.2
Requires-Dist: accelerate >=0.25.0
Requires-Dist: scipy >=1.10.1
Requires-Dist: pandas >=2.0.3
Requires-Dist: matplotlib >=3.7.2
Requires-Dist: opencv-python >=4.8.0.76
Requires-Dist: seaborn >=0.12.2
Requires-Dist: openai ==0.28.1
Requires-Dist: tqdm >=4.66.1
Requires-Dist: wrapt-timeout-decorator >=1.4.0
